ynab_csv_converter/__init__.py
ynab_csv_converter/__main__.py
ynab_csv_converter/formats/__init__.py
ynab_csv_converter/formats/americanexpress.py
ynab_csv_converter/formats/banknordik.py
ynab_csv_converter/formats/danskebank.py
ynab_csv_converter/formats/eika.py
ynab_csv_converter/formats/hypovereinsbank.py
ynab_csv_converter/formats/laanspar.py
ynab_csv_converter/formats/nordnet.py
ynab_csv_converter/formats/saxotradergo.py
ynab_csv_converter/formats/sparekassen-erhverv.py
ynab_csv_converter/formats/sparekassen.py
ynab_csv_converter/formats/starmoney.py
ynab_csv_converter/formats/ynab.py
ynab_csv_converter/formula-schema.yml
ynab_csv_converter-1.0.3.dist-info/METADATA
ynab_csv_converter-1.0.3.dist-info/WHEEL
ynab_csv_converter-1.0.3.dist-info/entry_points.txt
ynab_csv_converter-1.0.3.dist-info/RECORD
