Metadata-Version: 2.4
Name: ynab-csv-converter
Version: 1.0.3
Summary: Convert bank record CSV files in various formats to YNAB CSV format
License-Expression: Apache-2.0
Author: Anders Ingemann
Requires-Python: >= 3.11,<4
Classifier: Programming Language :: Python :: 3
Classifier: Programming Language :: Python :: 3.10
Requires-Dist: docopt (>=0.6.2,<1)
Requires-Dist: jsonschema (>=4.25.1,<5)
Requires-Dist: pyyaml (>=6.0,<7)
Requires-Dist: termcolor (>=1.1.0,<2)
